HISTORY.rst
LICENSE.txt
MANIFEST.in
README.rst
requirements.txt
setup.cfg
setup.py
yieldfrom.botocore.egg-info/PKG-INFO
yieldfrom.botocore.egg-info/SOURCES.txt
yieldfrom.botocore.egg-info/dependency_links.txt
yieldfrom.botocore.egg-info/namespace_packages.txt
yieldfrom.botocore.egg-info/not-zip-safe
yieldfrom.botocore.egg-info/requires.txt
yieldfrom.botocore.egg-info/top_level.txt
yieldfrom/botocore/__init__.py
yieldfrom/botocore/auth.py
yieldfrom/botocore/awsrequest.py
yieldfrom/botocore/client.py
yieldfrom/botocore/compat.py
yieldfrom/botocore/config.py
yieldfrom/botocore/credentials.py
yieldfrom/botocore/endpoint.py
yieldfrom/botocore/exceptions.py
yieldfrom/botocore/handlers.py
yieldfrom/botocore/hooks.py
yieldfrom/botocore/loaders.py
yieldfrom/botocore/model.py
yieldfrom/botocore/operation.py
yieldfrom/botocore/paginate.py
yieldfrom/botocore/parsers.py
yieldfrom/botocore/provider.py
yieldfrom/botocore/regions.py
yieldfrom/botocore/request_sessions_fixer.py
yieldfrom/botocore/response.py
yieldfrom/botocore/retryhandler.py
yieldfrom/botocore/serialize.py
yieldfrom/botocore/service.py
yieldfrom/botocore/session.py
yieldfrom/botocore/signers.py
yieldfrom/botocore/translate.py
yieldfrom/botocore/utils.py
yieldfrom/botocore/validate.py
yieldfrom/botocore/waiter.py
yieldfrom/botocore/data/aws/_endpoints.json
yieldfrom/botocore/data/aws/_retry.json
yieldfrom/botocore/data/aws/autoscaling/2011-01-01.normal.json
yieldfrom/botocore/data/aws/autoscaling/2011-01-01.paginators.json
yieldfrom/botocore/data/aws/cloudformation/2010-05-15.normal.json
yieldfrom/botocore/data/aws/cloudformation/2010-05-15.paginators.json
yieldfrom/botocore/data/aws/cloudfront/2014-05-31.normal.json
yieldfrom/botocore/data/aws/cloudfront/2014-05-31.paginators.json
yieldfrom/botocore/data/aws/cloudfront/2014-05-31.waiters.json
yieldfrom/botocore/data/aws/cloudfront/2014-10-21.normal.json
yieldfrom/botocore/data/aws/cloudfront/2014-10-21.paginators.json
yieldfrom/botocore/data/aws/cloudfront/2014-10-21.waiters.json
yieldfrom/botocore/data/aws/cloudfront/2014-11-06.normal.json
yieldfrom/botocore/data/aws/cloudfront/2014-11-06.paginators.json
yieldfrom/botocore/data/aws/cloudfront/2014-11-06.waiters.json
yieldfrom/botocore/data/aws/cloudhsm/2014-05-30.normal.json
