Metadata-Version: 1.1
Name: yieldfrom.botocore
Version: 0.1.6
Summary: asyncio port of botocore, the low-level, data-driven core of boto 3.
Home-page: https://github.com/rdbhost/yieldfromBotocore
Author: David Keeney
Author-email: dkeeney@rdbhost.com
License: Copyright 2012-2014 Amazon.com, Inc. or its affiliates. All Rights Reserved.
